duckdb_kernel/__init__.py
duckdb_kernel/__main__.py
duckdb_kernel/kernel.json
duckdb_kernel/kernel.py
duckdb_kernel/db/Column.py
duckdb_kernel/db/Connection.py
duckdb_kernel/db/Constraint.py
duckdb_kernel/db/DatabaseError.py
duckdb_kernel/db/ForeignKey.py
duckdb_kernel/db/Table.py
duckdb_kernel/db/__init__.py
duckdb_kernel/db/error/EmptyResultError.py
duckdb_kernel/db/error/__init__.py
duckdb_kernel/db/implementation/duckdb/Connection.py
duckdb_kernel/db/implementation/duckdb/__init__.py
duckdb_kernel/db/implementation/postgres/Connection.py
duckdb_kernel/db/implementation/postgres/__init__.py
duckdb_kernel/db/implementation/postgres/util.py
duckdb_kernel/db/implementation/sqlite/Connection.py
duckdb_kernel/db/implementation/sqlite/__init__.py
duckdb_kernel/magics/MagicCommand.py
duckdb_kernel/magics/MagicCommandCallback.py
duckdb_kernel/magics/MagicCommandException.py
duckdb_kernel/magics/MagicCommandHandler.py
duckdb_kernel/magics/MagicState.py
duckdb_kernel/magics/__init__.py
duckdb_kernel/parser/DCParser.py
duckdb_kernel/parser/LogicParser.py
duckdb_kernel/parser/ParserError.py
duckdb_kernel/parser/RAParser.py
duckdb_kernel/parser/__init__.py
duckdb_kernel/parser/elements/DCOperand.py
duckdb_kernel/parser/elements/LogicElement.py
duckdb_kernel/parser/elements/LogicOperand.py
duckdb_kernel/parser/elements/LogicOperator.py
duckdb_kernel/parser/elements/RABinaryOperator.py
duckdb_kernel/parser/elements/RAElement.py
duckdb_kernel/parser/elements/RAOperand.py
duckdb_kernel/parser/elements/RAOperator.py
duckdb_kernel/parser/elements/RARelationReference.py
duckdb_kernel/parser/elements/RAUnaryOperator.py
duckdb_kernel/parser/elements/__init__.py
duckdb_kernel/parser/elements/binary/Add.py
duckdb_kernel/parser/elements/binary/And.py
duckdb_kernel/parser/elements/binary/ArrowLeft.py
duckdb_kernel/parser/elements/binary/ConditionalSet.py
duckdb_kernel/parser/elements/binary/Cross.py
duckdb_kernel/parser/elements/binary/Difference.py
jupyter_duckdb-1.4.201.dist-info/METADATA
jupyter_duckdb-1.4.201.dist-info/WHEEL
jupyter_duckdb-1.4.201.dist-info/top_level.txt
jupyter_duckdb-1.4.201.dist-info/RECORD
