Metadata-Version: 2.4
Name: jupyter-duckdb
Version: 1.4.201
Summary: a basic wrapper kernel for DuckDB
Home-page: https://dbgit.prakinf.tu-ilmenau.de/ertr8623/jupyter-duckdb
Author: Eric Tröbs
Author-email: eric.troebs@tu-ilmenau.de
Project-URL: Bug Tracker, https://dbgit.prakinf.tu-ilmenau.de/ertr8623/jupyter-duckdb/-/issues
Classifier: Programming Language :: Python :: 3
Classifier: License :: OSI Approved :: MIT License
Classifier: Operating System :: OS Independent
Requires-Python: >=3.10
Requires-Dist: jupyter
Requires-Dist: graphviz==0.21
Requires-Dist: checkmarkandcross
Requires-Dist: duckdb==1.4.2
Dynamic: author
Dynamic: author-email
Dynamic: classifier
Dynamic: description
Dynamic: description-content-type
Dynamic: home-page
Dynamic: project-url
Dynamic: requires-dist
Dynamic: requires-python
Dynamic: summary
